segmentationMVC
segmentationUtils
